core/__init__.py
core/resource.py
core/delegation/__init__.py
core/delegation/responsehandler.py
core/exception/__init__.py
core/exception/exceptions.py
services/__init__.py
services/exchangerate.py
services/propeller.py
services/responses.py
interads-0.2.dist-info/LICENSE
interads-0.2.dist-info/METADATA
interads-0.2.dist-info/WHEEL
interads-0.2.dist-info/top_level.txt
interads-0.2.dist-info/RECORD
